README.rst
setup.cfg
setup.py
skerrorlearner/__init__.py
skerrorlearner/learn_error.py
skerrorlearner.egg-info/PKG-INFO
skerrorlearner.egg-info/SOURCES.txt
skerrorlearner.egg-info/dependency_links.txt
skerrorlearner.egg-info/requires.txt
skerrorlearner.egg-info/top_level.txt
skerrorlearner.egg-info/zip-safe