Metadata-Version: 1.1
Name: skerrorlearner
Version: 0.1.50
Summary: Skerrorlearner is an Error Learning Package for Machine Learning
Home-page: https://github.com/IndrashisDas/skerrorlearner
Author: Indrashis Das
Author-email: indrashisdas98@gmail.com
License: Apache License 2.0
Keywords: skerrorlearner,machine learning,artificial intelligence,scikit learn,sklearn,numpy,pandas,scipy,xgboost,lightgbm,catboost
Platform: UNKNOWN
Classifier: Development Status :: 5 - Production/Stable
Classifier: Intended Audience :: Developers
Classifier: Intended Audience :: Science/Research
Classifier: Topic :: Scientific/Engineering
Classifier: Topic :: Software Development
Classifier: License :: OSI Approved :: Apache Software License
Classifier: Operating System :: MacOS
Classifier: Operating System :: Unix
Classifier: Operating System :: Microsoft :: Windows
Classifier: Programming Language :: Python :: 3.5
Classifier: Programming Language :: Python :: 3.6
Classifier: Programming Language :: Python :: 3.7
Classifier: Programming Language :: Python :: 3.8
